{"name":"build-javascript","namedChunkGroups":{"app":{"name":"app","assets":[{"name":"webpack-runtime-0303bae070c96f9fa35e.js","size":4683},{"name":"styles.9d02b52cd6f643098d09.css","size":146582},{"name":"framework-d5a6dbf82e59c48838fd.js","size":140791},{"name":"app-f460c695a5bbbea95148.js","size":63410}],"filteredAssets":0,"assetsSize":355466,"filteredAuxiliaryAssets":49,"auxiliaryAssetsSize":1586235},"component---src-pages-404-tsx":{"name":"component---src-pages-404-tsx","assets":[{"name":"commons-ce401784f6f3c4a3941d.js","size":21291},{"name":"component---src-pages-404-tsx-b12b6d6f8d3d31a356dd.js","size":825}],"filteredAssets":0,"assetsSize":22116,"filteredAuxiliaryAssets":2,"auxiliaryAssetsSize":114946},"component---src-pages-markdown-remark-frontmatter-slug-tsx":{"name":"component---src-pages-markdown-remark-frontmatter-slug-tsx","assets":[{"name":"styles.9d02b52cd6f643098d09.css","size":146582},{"name":"commons-ce401784f6f3c4a3941d.js","size":21291},{"name":"component---src-pages-markdown-remark-frontmatter-slug-tsx-3c789ca5754f89ab438a.js","size":61509}],"filteredAssets":0,"assetsSize":229382,"filteredAuxiliaryAssets":48,"auxiliaryAssetsSize":1367487}},"assetsByChunkName":{"app":["webpack-runtime-0303bae070c96f9fa35e.js","styles.9d02b52cd6f643098d09.css","framework-d5a6dbf82e59c48838fd.js","app-f460c695a5bbbea95148.js"],"component---src-pages-404-tsx":["commons-ce401784f6f3c4a3941d.js","component---src-pages-404-tsx-b12b6d6f8d3d31a356dd.js"],"component---src-pages-markdown-remark-frontmatter-slug-tsx":["styles.9d02b52cd6f643098d09.css","commons-ce401784f6f3c4a3941d.js","component---src-pages-markdown-remark-frontmatter-slug-tsx-3c789ca5754f89ab438a.js"]},"childAssetsByChunkName":{}}